[
  {
    "imgsrc":"temp/relevant1.png",
    "title":"省政协领导视察 今年闽高校招生录取工作",
    "time":"60:00"
  },
  {
    "imgsrc":"temp/relevant2.png",
    "title":"福建农林大学： 坚持实践育人 引领青年成长",
    "time":"30:00"
  },
  {
    "imgsrc":"temp/relevant3.png",
    "title":"全省高校思想政治 工作会议在榕召开",
    "time":"20:45"
  },
  {
    "imgsrc":"temp/relevant4.png",
    "title":"福州大学：“三位一 体”打造“青椒”成长乐园",
    "time":"25:10"
  },
  {
    "imgsrc":"temp/relevant5.png",
    "title":"福建省教育厅 组织反腐倡廉警示教育",
    "time":"60:00"
  },
  {
    "imgsrc":"temp/relevant1.png",
    "title":"省政协领导视察 今年闽高校招生录取工作",
    "time":"60:00"
  },
  {
    "imgsrc":"temp/relevant2.png",
    "title":"福建农林大学： 坚持实践育人 引领青年成长",
    "time":"30:00"
  },
  {
    "imgsrc":"temp/relevant3.png",
    "title":"全省高校思想政治 工作会议在榕召开",
    "time":"20:45"
  }
]