[
  {
    "newsId":"1",
    "imgsrc":"temp/teacherdetail-tx.png",
    "name":"高中语文-邱秀天",
    "school":"福州一中"
  },
  {
    "newsId":"2",
    "imgsrc":"temp/teacherdetail-tx.png",
    "name":"高中语文-邱秀天",
    "school":"福州一中"
  },
  {
    "newsId":"3",
    "imgsrc":"temp/teacherdetail-tx.png",
    "name":"高中语文-邱秀天",
    "school":"福州一中"
  },
  {
    "newsId":"4",
    "imgsrc":"temp/teacherdetail-tx.png",
    "name":"高中语文-邱秀天",
    "school":"福州一中"
  },
  {
    "newsId":"5",
    "imgsrc":"temp/teacherdetail-tx.png",
    "name":"高中语文-邱秀天",
    "school":"福州一中"
  }
]